common/__init__.py
common/core/__init__.py
common/core/app.py
common/core/cli/__init__.py
common/core/cli/healthcheck.py
common/core/constants.py
common/core/logging.py
common/core/main.py
common/core/management/__init__.py
common/core/management/commands/__init__.py
common/core/management/commands/docgen.py
common/core/management/commands/start.py
common/core/management/commands/waitfordb.py
common/core/metrics.py
common/core/middleware.py
common/core/templates/docgen-metrics.md
common/core/urls.py
common/core/utils.py
common/core/views.py
common/environments/permissions.py
common/features/__init__.py
common/features/multivariate/__init__.py
common/features/multivariate/serializers.py
common/features/serializers.py
common/features/versioning/__init__.py
common/features/versioning/serializers.py
common/gunicorn/__init__.py
common/gunicorn/conf.py
common/gunicorn/constants.py
common/gunicorn/logging.py
common/gunicorn/metrics.py
common/gunicorn/metrics_server.py
common/gunicorn/middleware.py
common/gunicorn/utils.py
common/migrations/__init__.py
common/migrations/helpers/__init__.py
common/migrations/helpers/postgres_helpers.py
common/organisations/permissions.py
common/projects/permissions.py
common/prometheus/__init__.py
common/prometheus/utils.py
common/py.typed
common/test_tools/__init__.py
common/test_tools/plugin.py
common/test_tools/types.py
common/test_tools/utils.py
common/types.py
flagsmith_schemas/__init__.py
flagsmith_schemas/api.py
flagsmith_schemas/constants.py
flagsmith_schemas/dynamodb.py
flagsmith_schemas/py.typed
flagsmith_schemas/pydantic_types.py
flagsmith_schemas/types.py
flagsmith_schemas/utils.py
flagsmith_schemas/validators.py
task_processor/__init__.py
task_processor/admin.py
task_processor/apps.py
task_processor/decorators.py
task_processor/exceptions.py
task_processor/health.py
task_processor/managers.py
task_processor/metrics.py
task_processor/migrations/0001_initial.py
task_processor/migrations/0002_healthcheckmodel.py
flagsmith_common-3.3.0.dist-info/licenses/LICENSE
flagsmith_common-3.3.0.dist-info/WHEEL
flagsmith_common-3.3.0.dist-info/entry_points.txt
flagsmith_common-3.3.0.dist-info/METADATA
flagsmith_common-3.3.0.dist-info/RECORD
