Metadata-Version: 2.4
Name: flagsmith-common
Version: 3.3.0
Summary: Flagsmith's common library
Author: Matthew Elwell, Gagan Trivedi, Kim Gustyr, Zach Aysan, Francesco Lo Franco, Rodrigo López Dato, Evandro Myller, Wadii Zaim
License-Expression: BSD-3-Clause
License-File: LICENSE
Classifier: Framework :: Django
Classifier: Framework :: Pytest
Classifier: Intended Audience :: Developers
Classifier: License :: OSI Approved :: BSD License
Requires-Dist: django>4,<6 ; extra == 'common-core'
Requires-Dist: django-health-check ; extra == 'common-core'
Requires-Dist: djangorestframework-recursive ; extra == 'common-core'
Requires-Dist: djangorestframework ; extra == 'common-core'
Requires-Dist: drf-spectacular>=0.28.0,<1 ; extra == 'common-core'
Requires-Dist: drf-writable-nested ; extra == 'common-core'
Requires-Dist: environs<15 ; extra == 'common-core'
Requires-Dist: gunicorn>=19.1 ; extra == 'common-core'
Requires-Dist: prometheus-client>=0.0.16 ; extra == 'common-core'
Requires-Dist: psycopg2-binary>=2.9,<3 ; extra == 'common-core'
Requires-Dist: requests ; extra == 'common-core'
Requires-Dist: simplejson>=3,<4 ; extra == 'common-core'
Requires-Dist: simplejson ; extra == 'flagsmith-schemas'
Requires-Dist: typing-extensions ; extra == 'flagsmith-schemas'
Requires-Dist: flagsmith-flag-engine>6 ; extra == 'flagsmith-schemas'
Requires-Dist: backoff>=2.2.1,<3.0.0 ; extra == 'task-processor'
Requires-Dist: django>4,<6 ; extra == 'task-processor'
Requires-Dist: django-health-check ; extra == 'task-processor'
Requires-Dist: prometheus-client>=0.0.16 ; extra == 'task-processor'
Requires-Dist: pyfakefs>=5,<6 ; extra == 'test-tools'
Requires-Dist: pytest-django>=4,<5 ; extra == 'test-tools'
Maintainer: Flagsmith Team
Maintainer-email: Flagsmith Team <support@flagsmith.com>
Requires-Python: >=3.11, <4.0
Project-URL: Changelog, https://github.com/flagsmith/flagsmith-common/blob/main/CHANGELOG.md
Project-URL: Download, https://github.com/flagsmith/flagsmith-common/releases
Project-URL: Homepage, https://flagsmith.com
Project-URL: Issues, https://github.com/flagsmith/flagsmith-common/issues
Project-URL: Repository, https://github.com/flagsmith/flagsmith-common
Provides-Extra: common-core
Provides-Extra: flagsmith-schemas
Provides-Extra: task-processor
Provides-Extra: test-tools
